Hooke/__init__.py
Hooke/compare.py
Hooke/extract.py
Hooke/main.py
Hooke/order.py
Hooke/search.py
Hooke/test/test.txt
pyHooke-0.2.1.dist-info/LICENSE
pyHooke-0.2.1.dist-info/METADATA
pyHooke-0.2.1.dist-info/WHEEL
pyHooke-0.2.1.dist-info/dependency_links.txt
pyHooke-0.2.1.dist-info/top_level.txt
pyHooke-0.2.1.dist-info/RECORD
