Metadata-Version: 2.1
Name: pyHooke
Version: 0.2.1
Summary: Open source plagiarism checker
Home-page: http://github.com/oekshido/hooke
Author: oekshido
Author-email: oekshido@gmail.com
License: Apache-2.0
Keywords: plagiarism nlp plag scan levenshtein
Platform: UNKNOWN
Classifier: Development Status :: 3 - Alpha
Classifier: License :: OSI Approved :: Apache Software License
Classifier: Programming Language :: Python :: 3
Classifier: Topic :: Text Processing :: Linguistic
Requires-Dist: fuzzysearch
Requires-Dist: tika
Requires-Dist: wget
Requires-Dist: BeautifulSoup4
Requires-Dist: nltk
Requires-Dist: textract
Requires-Dist: Google-Search-API
